LICENSE.md
MANIFEST.in
README.md
setup.py
django_poller.egg-info/PKG-INFO
django_poller.egg-info/SOURCES.txt
django_poller.egg-info/dependency_links.txt
django_poller.egg-info/top_level.txt
poll/__init__.py
poll/admin.py
poll/forms.py
poll/models.py
poll/tests.py
poll/urls.py
poll/views.py
poll/migrations/0001_initial.py
poll/migrations/__init__.py
poll/static/css/poll_style.css
poll/templates/general.html
poll/templates/polls.html
poll/templatetags/__init__.py
poll/templatetags/poll_tags.py
poll/tools/__init__.py
poll/tools/helper.py